msa_toolbox/__init__.py
msa_toolbox/config.py
msa_toolbox/main.py
msa_toolbox/active_learning/__init__.py
msa_toolbox/active_learning/active_learning_main.py
msa_toolbox/active_learning/active_learning_main_api.py
msa_toolbox/active_learning/active_learning_methods.py
msa_toolbox/active_learning/dfal/__init__.py
msa_toolbox/active_learning/dfal/dfal_method.py
msa_toolbox/active_learning/entropy/__init__.py
msa_toolbox/active_learning/entropy/entropy_method.py
msa_toolbox/active_learning/kcenter/__init__.py
msa_toolbox/active_learning/kcenter/kcenter_greedy.py
msa_toolbox/active_learning/kcenter/kcenter_method.py
msa_toolbox/active_learning/kcenter/utils.py
msa_toolbox/active_learning/montecarlo/__init__.py
msa_toolbox/active_learning/montecarlo/montecarlo_method.py
msa_toolbox/active_learning/random/__init__.py
msa_toolbox/active_learning/random/random_method.py
msa_toolbox/active_learning/vaal/__init__.py
msa_toolbox/active_learning/vaal/vaal_method.py
msa_toolbox/active_learning/vaal/vaal_models.py
msa_toolbox/datasets/__init__.py
msa_toolbox/datasets/image/__init__.py
msa_toolbox/datasets/image/caltech256.py
msa_toolbox/datasets/image/cifar.py
msa_toolbox/datasets/image/cubs200.py
msa_toolbox/datasets/image/custom_dataset.py
msa_toolbox/datasets/image/diabetic5.py
msa_toolbox/datasets/image/imagenet.py
msa_toolbox/datasets/image/indoor67.py
msa_toolbox/datasets/image/mnist.py
msa_toolbox/datasets/image/svhn.py
msa_toolbox/datasets/image/tinyimagenet200.py
msa_toolbox/datasets/text/__init__.py
msa_toolbox/defence/__init__.py
msa_toolbox/defence/defence_main.py
msa_toolbox/defence/defence_main_api.py
msa_toolbox/defence/adaptive_misinformation/__init__.py
msa_toolbox/defence/adaptive_misinformation/adaptive_misinformation.py
msa_toolbox/defence/no_defence/__init__.py
msa_toolbox/defence/no_defence/no_defence.py
msa_toolbox/defence/no_defence/no_defence_clarifai_api.py
msa_toolbox/defence/no_defence/no_defence_huggingface_api.py
msa_toolbox-2.0.0.dist-info/METADATA
msa_toolbox-2.0.0.dist-info/WHEEL
msa_toolbox-2.0.0.dist-info/entry_points.txt
msa_toolbox-2.0.0.dist-info/top_level.txt
msa_toolbox-2.0.0.dist-info/RECORD
