Metadata-Version: 2.1
Name: msa_toolbox
Version: 2.0.0
Summary: MSA Toolbox
Author: Akshit, Khushdev, Sumit
Author-email: sumit20249@iiitd.ac.in
Keywords: msa
Classifier: Development Status :: 3 - Alpha
Classifier: Intended Audience :: Developers
Classifier: Programming Language :: Python :: 3
Classifier: Operating System :: Unix
Classifier: Operating System :: MacOS :: MacOS X
Classifier: Operating System :: Microsoft :: Windows
Requires-Dist: numpy >=1.18.0
Requires-Dist: scikit-learn <1.2.0,>=0.22.2
Requires-Dist: six
Requires-Dist: setuptools
Requires-Dist: tqdm
Requires-Dist: Flask
Requires-Dist: scipy >=1.7.3
Requires-Dist: matplotlib >=3.5.1
Requires-Dist: yacs
Requires-Dist: gradio
Requires-Dist: gradio-client
Requires-Dist: huggingface-hub
Requires-Dist: ipykernel
Requires-Dist: pylint
Requires-Dist: PyYAML
Requires-Dist: torch
Requires-Dist: torchvision
Provides-Extra: all
Requires-Dist: torch ; extra == 'all'
Requires-Dist: torchvision ; extra == 'all'
Requires-Dist: xgboost ; extra == 'all'
Requires-Dist: pandas ; extra == 'all'
Requires-Dist: kornia ; extra == 'all'
Requires-Dist: matplotlib ; extra == 'all'
Requires-Dist: Pillow ; extra == 'all'
Requires-Dist: statsmodels ; extra == 'all'
Requires-Dist: pydub ; extra == 'all'
Requires-Dist: resampy ; extra == 'all'
Requires-Dist: ffmpeg-python ; extra == 'all'
Requires-Dist: cma ; extra == 'all'
Requires-Dist: librosa ; extra == 'all'
Requires-Dist: opencv-python ; extra == 'all'
Requires-Dist: numba ; extra == 'all'
Provides-Extra: non_framework
Requires-Dist: matplotlib ; extra == 'non_framework'
Requires-Dist: Pillow ; extra == 'non_framework'
Requires-Dist: statsmodels ; extra == 'non_framework'
Requires-Dist: pydub ; extra == 'non_framework'
Requires-Dist: resampy ; extra == 'non_framework'
Requires-Dist: ffmpeg-python ; extra == 'non_framework'
Requires-Dist: cma ; extra == 'non_framework'
Requires-Dist: pandas ; extra == 'non_framework'
Requires-Dist: librosa ; extra == 'non_framework'
Requires-Dist: opencv-python ; extra == 'non_framework'
Requires-Dist: pytest ; extra == 'non_framework'
Requires-Dist: pytest-flake8 ; extra == 'non_framework'
Requires-Dist: pytest-mock ; extra == 'non_framework'
Requires-Dist: pytest-cov ; extra == 'non_framework'
Requires-Dist: codecov ; extra == 'non_framework'
Requires-Dist: requests ; extra == 'non_framework'
Requires-Dist: sortedcontainers ; extra == 'non_framework'
Requires-Dist: numba ; extra == 'non_framework'
Provides-Extra: pytorch
Requires-Dist: torch ; extra == 'pytorch'
Requires-Dist: torchvision ; extra == 'pytorch'
Provides-Extra: pytorch_audio
Requires-Dist: torch ; extra == 'pytorch_audio'
Requires-Dist: torchvision ; extra == 'pytorch_audio'
Requires-Dist: torchaudio ; extra == 'pytorch_audio'
Requires-Dist: pydub ; extra == 'pytorch_audio'
Requires-Dist: resampy ; extra == 'pytorch_audio'
Requires-Dist: librosa ; extra == 'pytorch_audio'
Provides-Extra: pytorch_image
Requires-Dist: torch ; extra == 'pytorch_image'
Requires-Dist: torchvision ; extra == 'pytorch_image'
Requires-Dist: kornia ; extra == 'pytorch_image'
Requires-Dist: Pillow ; extra == 'pytorch_image'
Requires-Dist: ffmpeg-python ; extra == 'pytorch_image'
Requires-Dist: opencv-python ; extra == 'pytorch_image'
Provides-Extra: xgboost
Requires-Dist: xgboost ; extra == 'xgboost'
